{
  "filename": "documentation_zh-cn_unreal-engine_paper-2d-settings-in-the-unreal-engine-project-settings",
  "sourceFile": "C:\\Users\\yarnb\\unreal-engine-knowledge-graph-mcp\\sources\\docs\\documentation_zh-cn_unreal-engine_paper-2d-settings-in-the-unreal-engine-project-settings.md",
  "triples": [
    {
      "subject": "Paper 2D",
      "predicate": "包含",
      "object": "试验性功能",
      "context": "Paper 2D模块包含试验性功能设置，帮助学习者了解该模块的完整功能范围",
      "direction": "unidirectional",
      "confidence": 0.9
    },
    {
      "subject": "Paper 2D",
      "predicate": "包含",
      "object": "设置",
      "context": "Paper 2D模块包含常规设置选项，是学习该模块功能的基础配置部分",
      "direction": "unidirectional",
      "confidence": 0.9
    },
    {
      "subject": "试验性功能",
      "predicate": "包含",
      "object": "Sprite图集组",
      "context": "试验性功能中包含Sprite图集组设置，帮助学习者了解高级但尚不稳定的功能",
      "direction": "unidirectional",
      "confidence": 0.9
    },
    {
      "subject": "试验性功能",
      "predicate": "包含",
      "object": "地貌样条线编辑",
      "context": "试验性功能中包含2D地貌样条线编辑功能，扩展学习者对2D地形编辑的认识",
      "direction": "unidirectional",
      "confidence": 0.9
    },
    {
      "subject": "Sprite图集组",
      "predicate": "用于",
      "object": "Sprite分配",
      "context": "Sprite图集组功能专门用于管理Sprite的纹理分配，帮助学习者理解资源优化方法",
      "direction": "unidirectional",
      "confidence": 0.9
    },
    {
      "subject": "地貌样条线编辑",
      "predicate": "需要",
      "object": "编辑器重启",
      "context": "启用地貌样条线编辑需要重启编辑器，这是学习者需要注意的重要工作流程",
      "direction": "unidirectional",
      "confidence": 0.9
    },
    {
      "subject": "设置",
      "predicate": "包含",
      "object": "调整Sprite数据大小",
      "context": "常规设置中包含Sprite数据自动调整功能，是学习Sprite资源管理的重要概念",
      "direction": "unidirectional",
      "confidence": 0.9
    },
    {
      "subject": "调整Sprite数据大小",
      "predicate": "影响",
      "object": "Sprite数据",
      "context": "该设置会影响纹理空间中的各种Sprite数据，帮助学习者理解资源调整的连锁反应",
      "direction": "unidirectional",
      "confidence": 0.9
    },
    {
      "subject": "Sprite数据",
      "predicate": "包括",
      "object": "插槽",
      "context": "Sprite数据包含插槽信息，帮助学习者全面了解Sprite的组成部分",
      "direction": "unidirectional",
      "confidence": 0.8
    },
    {
      "subject": "Sprite数据",
      "predicate": "包括",
      "object": "枢轴点",
      "context": "Sprite数据包含枢轴点信息，这是学习Sprite定位和旋转的基础知识",
      "direction": "unidirectional",
      "confidence": 0.8
    },
    {
      "subject": "Sprite数据",
      "predicate": "包括",
      "object": "碰撞几何体",
      "context": "Sprite数据包含碰撞几何体信息，关联到物理交互的学习内容",
      "direction": "unidirectional",
      "confidence": 0.8
    },
    {
      "subject": "Paper 2D",
      "predicate": "关联",
      "object": "UI开发",
      "context": "Paper 2D与UI开发相关，文档中的标签提示了这种关联性",
      "direction": "bidirectional",
      "confidence": 0.7
    }
  ],
  "timestamp": "2025-06-15T20:18:59.824Z",
  "warnings": [],
  "metadata": {
    "fileSize": 1901,
    "contentLength": 1421,
    "processingTimeMs": 38190
  }
}